arya/__init__.py
arya/__main__.py
arya/apicxmljson.py
arya/arya.py
arya/getconfigfromapic.py
arya/version.py
arya-1.1.5.data/scripts/apicxmljson.py
arya-1.1.5.data/scripts/arya.py
arya-1.1.5.data/scripts/getconfigfromapic.py
arya-1.1.5.dist-info/DESCRIPTION.rst
arya-1.1.5.dist-info/entry_points.txt
arya-1.1.5.dist-info/METADATA
arya-1.1.5.dist-info/metadata.json
arya-1.1.5.dist-info/RECORD
arya-1.1.5.dist-info/top_level.txt
arya-1.1.5.dist-info/WHEEL
