Metadata-Version: 2.0
Name: arya
Version: 1.1.5
Summary: APIC Rest to pYthon Adapter
Home-page: https://github.com/datacenter/arya
Author: Paul Lesiak
Author-email: palesiak@cisco.com
License: APIC Rest Python Adapter (arya)
